meldtools/__init__.py
meldtools/__main__.py
meldtools/handlers.py
meldtools/models.py
meldtools-0.2.0.dist-info/entry_points.txt
meldtools-0.2.0.dist-info/WHEEL
meldtools-0.2.0.dist-info/METADATA
meldtools-0.2.0.dist-info/RECORD
