Metadata-Version: 2.1
Name: meldtools
Version: 0.2.0
Summary: Tools used to work with MELD texts
License: MIT
Author: Michał Adamczyk
Author-email: michal.adamczyk.1990@gmail.com
Requires-Python: >=3.8,<4.0
Classifier: License :: OSI Approved :: MIT License
Classifier: Programming Language :: Python :: 3
Classifier: Programming Language :: Python :: 3.8
Requires-Dist: click (>=7.1.2,<8.0.0)
Requires-Dist: pandas (>=1.0.5,<2.0.0)
Requires-Dist: pandasql (>=0.7.3,<0.8.0)
